freethreading/__init__.py
free_threading-1.1.0.dist-info/WHEEL
free_threading-1.1.0.dist-info/METADATA
free_threading-1.1.0.dist-info/RECORD
