Metadata-Version: 2.4
Name: free-threading
Version: 1.1.0
Summary: Thread-first true parallelism
Keywords: gil,nogil,thread,process,worker,threading,free-threading,multithreading,multiprocessing,concurrency,parallelism
Author: Iskander Gaba
Author-email: Iskander Gaba <iskander@hey.com>
License-Expression: MIT
Classifier: Programming Language :: Python :: 3
Classifier: Programming Language :: Python :: 3.10
Classifier: Programming Language :: Python :: 3.11
Classifier: Programming Language :: Python :: 3.12
Classifier: Programming Language :: Python :: 3.13
Classifier: Programming Language :: Python :: 3.14
Requires-Python: >=3.10
Project-URL: Documentation, https://freethreading.readthedocs.io
Project-URL: Repository, https://github.com/iskandergaba/free-threading
